crontask/__init__.py
crontask/_version.py
crontask/conf.py
crontask/tasks.py
crontask/utils.py
crontask/management/__init__.py
crontask/management/commands/__init__.py
crontask/management/commands/crontask.py
django_crontask-1.1.3.dist-info/licenses/LICENSE
django_crontask-1.1.3.dist-info/WHEEL
django_crontask-1.1.3.dist-info/METADATA
django_crontask-1.1.3.dist-info/RECORD
