Metadata-Version: 2.4
Name: django-crontask
Version: 1.1.3
Summary: Cron style scheduler for Django's task framework.
Keywords: Django,cron,tasks,scheduler
Author-email: Rust Saiargaliev <fly.amureki@gmail.com>, Johannes Maron <johannes@maron.family>, Mostafa Mohamed <mostafa.anm91@gmail.com>, Jacqueline Kraus <jacquelinekraus1992@gmail.com>
Requires-Python: >=3.12
Classifier: Development Status :: 5 - Production/Stable
Classifier: Programming Language :: Python
Classifier: Environment :: Web Environment
Classifier: License :: OSI Approved :: BSD License
Classifier: Intended Audience :: Developers
Classifier: Operating System :: Microsoft :: Windows
Classifier: Operating System :: MacOS :: MacOS X
Classifier: Operating System :: POSIX
Classifier: Topic :: Communications :: Email
Classifier: Topic :: Text Processing :: Markup :: Markdown
Classifier: Topic :: Software Development
Classifier: Programming Language :: Python
Classifier: Programming Language :: Python :: 3
Classifier: Programming Language :: Python :: 3 :: Only
Classifier: Programming Language :: Python :: 3.12
Classifier: Programming Language :: Python :: 3.13
Classifier: Programming Language :: Python :: 3.14
Classifier: Framework :: Django
Classifier: Framework :: Django :: 6.0
License-File: LICENSE
Requires-Dist: apscheduler
Requires-Dist: django>=6.0
Requires-Dist: redis ; extra == "redis"
Requires-Dist: sentry-sdk ; extra == "sentry"
Project-URL: Changelog, https://github.com/codingjoe/django-crontask/releases
Project-URL: Project-URL, https://github.com/codingjoe/django-crontask
Provides-Extra: redis
Provides-Extra: sentry
